bloatectomy/__init__.py
bloatectomy/bloatectomy.py
bloatectomy-0.0.12.dist-info/LICENSE
bloatectomy-0.0.12.dist-info/METADATA
bloatectomy-0.0.12.dist-info/WHEEL
bloatectomy-0.0.12.dist-info/top_level.txt
bloatectomy-0.0.12.dist-info/RECORD
