Metadata-Version: 2.1
Name: bloatectomy
Version: 0.0.12
Summary: Bloatectomy: a method for the identification and removal of duplicate text in the bloated notes of electronic health records and other documents.
Home-page: https://github.com/MIT-LCP/bloatectomy
Author: Summer Rankin, Roselie Bright, Katherine Dowdy
Author-email: summerKRankin@gmail.com
License: GPLv3
Keywords: python,medical informatics,electronic health records,electronic medical records,public health informatics,clinical information extraction,informatics,natural language processing
Platform: UNKNOWN
Classifier: Programming Language :: Python
Classifier: Programming Language :: Python :: 3 :: Only
Classifier: Programming Language :: Python :: 3.7
Classifier: Programming Language :: Python :: 3.8
Classifier: License :: OSI Approved :: GNU General Public License v3 (GPLv3)
Classifier: Operating System :: OS Independent
Classifier: Intended Audience :: Developers
Classifier: Intended Audience :: Science/Research
Classifier: Topic :: Scientific/Engineering
Classifier: Topic :: Scientific/Engineering :: Information Analysis
Classifier: Topic :: Software Development :: Libraries :: Python Modules
Classifier: Topic :: Text Processing
Classifier: Topic :: Utilities
Requires-Python: >=3.7
